cubicweb_prometheus/__init__.py
cubicweb_prometheus/__pkginfo__.py
cubicweb_prometheus/views.py
cubicweb_prometheus/i18n/en.po
cubicweb_prometheus/i18n/es.po
cubicweb_prometheus/i18n/fr.po
cubicweb_prometheus-0.7.1.dist-info/METADATA
cubicweb_prometheus-0.7.1.dist-info/WHEEL
cubicweb_prometheus-0.7.1.dist-info/entry_points.txt
cubicweb_prometheus-0.7.1.dist-info/top_level.txt
cubicweb_prometheus-0.7.1.dist-info/RECORD
