Metadata-Version: 2.4
Name: cubicweb-prometheus
Version: 0.7.1
Summary: Exporting prometheus metrics
Home-page: https://forge.extranet.logilab.fr/cubicweb/cubes/prometheus
Author: LOGILAB S.A. (Paris, FRANCE)
Author-email: contact@logilab.fr
License: LGPL
Classifier: Environment :: Web Environment
Classifier: Framework :: CubicWeb
Classifier: Programming Language :: Python :: 3
Classifier: Programming Language :: JavaScript
Requires-Python: >=3.9.2
Requires-Dist: cubicweb<6.0.0,>=4.5.2
Requires-Dist: prometheus-client<0.17.0,>=0.16.0
Requires-Dist: uwsgi-prometheus<2.0.0,>=1.0.0
Dynamic: author
Dynamic: author-email
Dynamic: classifier
Dynamic: description
Dynamic: description-content-type
Dynamic: home-page
Dynamic: license
Dynamic: requires-dist
Dynamic: requires-python
Dynamic: summary
